LICENSE.md
README.md
setup.cfg
setup.py
src/detext/__init__.py
src/detext/args.py
src/detext/metaclass.py
src/detext/run_detext.py
src/detext.egg-info/PKG-INFO
src/detext.egg-info/SOURCES.txt
src/detext.egg-info/dependency_links.txt
src/detext.egg-info/requires.txt
src/detext.egg-info/top_level.txt
src/detext/examples/__init__.py
src/detext/examples/embedding_layer_example.py
src/detext/examples/vocab_layer_example.py
src/detext/layers/__init__.py
src/detext/layers/bert_layer.py
src/detext/layers/cnn_layer.py
src/detext/layers/embedding_layer.py
src/detext/layers/feature_grouper.py
src/detext/layers/feature_name_type_converter.py
src/detext/layers/feature_normalizer.py
src/detext/layers/feature_rescaler.py
src/detext/layers/id_embed_layer.py
src/detext/layers/interaction_layer.py
src/detext/layers/lstm_layer.py
src/detext/layers/multi_layer_perceptron.py
src/detext/layers/output_transform_layer.py
src/detext/layers/representation_layer.py
src/detext/layers/scoring_layer.py
src/detext/layers/shallow_tower_layer.py
src/detext/layers/sparse_embedding_layer.py
src/detext/layers/vocab_layer.py
src/detext/train/__init__.py
src/detext/train/constant.py
src/detext/train/data_fn.py
src/detext/train/loss.py
src/detext/train/metrics.py
src/detext/train/model.py
src/detext/train/optimization.py
src/detext/train/train.py
src/detext/train/train_flow_helper.py
src/detext/train/train_model_helper.py
src/detext/utils/__init__.py
src/detext/utils/distributed_utils.py
src/detext/utils/layer_utils.py
src/detext/utils/parsing_utils.py
src/detext/utils/vocab_utils.py
src/detext/utils/testing/__init__.py
src/detext/utils/testing/data_setup.py
src/detext/utils/testing/testing_utils.py
src/libert/__init__.py
src/libert/preprocess.py
src/smart_compose/__init__.py
src/smart_compose/args.py
src/smart_compose/run_smart_compose.py
src/smart_compose/layers/__init__.py
src/smart_compose/layers/beam_search.py
src/smart_compose/layers/embedding_layer.py
src/smart_compose/layers/prefix_search.py
src/smart_compose/layers/vocab_layer.py
src/smart_compose/train/__init__.py
src/smart_compose/train/data_fn.py
src/smart_compose/train/losses.py
