Metadata-Version: 2.1
Name: detext
Version: 3.2.0
Summary: UNKNOWN
Home-page: UNKNOWN
License: BSD-2-CLAUSE
Platform: UNKNOWN
Classifier: Programming Language :: Python :: 3.7
Classifier: Programming Language :: Python :: 3.8
Classifier: Programming Language :: Python :: 3.9
Classifier: Topic :: Scientific/Engineering :: Artificial Intelligence
Classifier: Topic :: Software Development :: Libraries
Classifier: Intended Audience :: Science/Research
Classifier: Intended Audience :: Developers
Classifier: License :: OSI Approved
License-File: LICENSE.md
